<?xml version="1.0" encoding="UTF-8"?>
<!DOCTYPE QtCreatorProfiles>
<!-- Written by QtCreator 4.11.2, 2020-04-14T15:04:47. -->
<qtcreator>
 <data>
  <variable>Kit.IrrelevantAspects</variable>
  <valuelist type="QVariantList"/>
 </data>
 <data>
  <variable>Profile.0</variable>
  <valuemap type="QVariantMap">
   <value type="bool" key="PE.Profile.AutoDetected">false</value>
   <value type="QString" key="PE.Profile.AutoDetectionSource"></value>
   <valuemap type="QVariantMap" key="PE.Profile.Data">
    <value type="QString" key="Android.GdbServer.Information"></value>
    <valuelist type="QVariantList" key="CMake.ConfigurationKitInformation">
     <value type="QString">CMAKE_TOOLCHAIN_FILE:INTERNAL=/home/jboehme/Development/openwrt-sdk/sdk/openwrt.toolchain.cmake</value>
    </valuelist>
    <valuemap type="QVariantMap" key="CMake.GeneratorKitInformation">
     <value type="QString" key="ExtraGenerator">CodeBlocks</value>
     <value type="QString" key="Generator">Unix Makefiles</value>
     <value type="QString" key="Platform"></value>
     <value type="QString" key="Toolset"></value>
    </valuemap>
    <value type="QString" key="CMakeProjectManager.CMakeKitInformation">{9a4ea4bc-ae7e-4a8c-a1fd-57365ba1836a}</value>
    <value type="QString" key="Debugger.Information">{7aa45a62-f81c-4fc4-abbe-3f966a8d01e0}</value>
    <value type="QString" key="PE.Profile.Device">{db5d9aa6-9ceb-410a-b3fa-28981b07d2ef}</value>
    <value type="QString" key="PE.Profile.DeviceType">GenericLinuxOsType</value>
    <value type="QString" key="PE.Profile.SysRoot">/home/build/openwrt/staging_dir/toolchain-mips_34kc_gcc-5.3.0_musl-1.1.14</value>
    <valuemap type="QVariantMap" key="PE.Profile.ToolChainsV3">
     <value type="QByteArray" key="C">{41d012be-e7b8-451f-8bce-36ab917ba86b}</value>
     <value type="QByteArray" key="Cxx">{c595ef29-e38b-48d7-8e44-c60dfca3c00c}</value>
    </valuemap>
    <value type="int" key="QtSupport.QtInformation">-1</value>
   </valuemap>
   <value type="QString" key="PE.Profile.DeviceTypeForIcon"></value>
   <value type="QString" key="PE.Profile.Icon"></value>
   <value type="QString" key="PE.Profile.Id">{12eb42c3-3889-4982-b295-f32c3055f19f}</value>
   <valuelist type="QVariantList" key="PE.Profile.MutableInfo"/>
   <value type="QString" key="PE.Profile.Name">OpenWRT mips 32bit (8devices)</value>
   <value type="bool" key="PE.Profile.SDK">false</value>
   <valuelist type="QVariantList" key="PE.Profile.StickyInfo"/>
  </valuemap>
 </data>
 <data>
  <variable>Profile.1</variable>
  <valuemap type="QVariantMap">
   <value type="bool" key="PE.Profile.AutoDetected">false</value>
   <value type="QString" key="PE.Profile.AutoDetectionSource"></value>
   <valuemap type="QVariantMap" key="PE.Profile.Data">
    <value type="QString" key="Android.GdbServer.Information"></value>
    <valuelist type="QVariantList" key="CMake.ConfigurationKitInformation">
     <value type="QString">CMAKE_TOOLCHAIN_FILE:INTERNAL=/home/jboehme/Development/openwrt-sdk/sdk/openwrt.toolchain.cmake</value>
    </valuelist>
    <valuemap type="QVariantMap" key="CMake.GeneratorKitInformation">
     <value type="QString" key="ExtraGenerator">CodeBlocks</value>
     <value type="QString" key="Generator">Unix Makefiles</value>
     <value type="QString" key="Platform"></value>
     <value type="QString" key="Toolset"></value>
    </valuemap>
    <value type="QString" key="CMakeProjectManager.CMakeKitInformation">{9a4ea4bc-ae7e-4a8c-a1fd-57365ba1836a}</value>
    <value type="QString" key="Debugger.Information">{72dc20b9-2967-4e3d-9254-63b929723a0f}</value>
    <value type="QString" key="PE.Profile.Device">{db5d9aa6-9ceb-410a-b3fa-28981b07d2ef}</value>
    <value type="QString" key="PE.Profile.DeviceType">GenericLinuxOsType</value>
    <value type="QString" key="PE.Profile.SysRoot">/home/build/openwrt/staging_dir/toolchain-mips_24kc_gcc-7.3.0_musl</value>
    <valuemap type="QVariantMap" key="PE.Profile.ToolChainsV3">
     <value type="QByteArray" key="C">{82a30d99-3d46-49a7-86f3-df1ec0079c1e}</value>
     <value type="QByteArray" key="Cxx">{470c651f-2872-44a0-a24a-c3aacbeec834}</value>
    </valuemap>
    <value type="int" key="QtSupport.QtInformation">-1</value>
   </valuemap>
   <value type="QString" key="PE.Profile.DeviceTypeForIcon"></value>
   <value type="QString" key="PE.Profile.Icon"></value>
   <value type="QString" key="PE.Profile.Id">{1a1d66cf-ecf2-4d06-a73c-d53e1bd29c02}</value>
   <valuelist type="QVariantList" key="PE.Profile.MutableInfo"/>
   <value type="QString" key="PE.Profile.Name">OpenWRT mips 32bit (ar71xx)</value>
   <value type="bool" key="PE.Profile.SDK">false</value>
   <valuelist type="QVariantList" key="PE.Profile.StickyInfo"/>
  </valuemap>
 </data>
 <data>
  <variable>Profile.10</variable>
  <valuemap type="QVariantMap">
   <value type="bool" key="PE.Profile.AutoDetected">true</value>
   <value type="QString" key="PE.Profile.AutoDetectionSource"></value>
   <valuemap type="QVariantMap" key="PE.Profile.Data">
    <valuelist type="QVariantList" key="CMake.ConfigurationKitInformation">
     <value type="QString">QT_QMAKE_EXECUTABLE:STRING=%{Qt:qmakeExecutable}</value>
     <value type="QString">CMAKE_PREFIX_PATH:STRING=%{Qt:QT_INSTALL_PREFIX}</value>
     <value type="QString">CMAKE_C_COMPILER:STRING=%{Compiler:Executable:C}</value>
     <value type="QString">CMAKE_CXX_COMPILER:STRING=%{Compiler:Executable:Cxx}</value>
    </valuelist>
    <valuemap type="QVariantMap" key="CMake.GeneratorKitInformation">
     <value type="QString" key="ExtraGenerator">CodeBlocks</value>
     <value type="QString" key="Generator">Unix Makefiles</value>
     <value type="QString" key="Platform"></value>
     <value type="QString" key="Toolset"></value>
    </valuemap>
    <value type="QString" key="CMakeProjectManager.CMakeKitInformation">{1eea85c6-2861-425e-ad10-561cb4b2db65}</value>
    <value type="QString" key="Debugger.Information">{7aa45a62-f81c-4fc4-abbe-3f966a8d01e0}</value>
    <value type="QString" key="PE.Profile.Device">Desktop Device</value>
    <value type="QString" key="PE.Profile.DeviceType">Desktop</value>
    <valuemap type="QVariantMap" key="PE.Profile.ToolChains">
     <value type="QString" key="C">x86-linux-generic-elf-64bit</value>
     <value type="QString" key="Cxx">x86-linux-generic-elf-64bit</value>
    </valuemap>
    <valuemap type="QVariantMap" key="PE.Profile.ToolChainsV3">
     <value type="QByteArray" key="C">{040a20c4-98d6-4bb4-b6c0-cd77d6c2f903}</value>
     <value type="QByteArray" key="Cxx">{57008a9f-0a5c-41af-ad89-c3f784370d39}</value>
    </valuemap>
    <value type="QString" key="QtSupport.QtInformation">SDK.qt.qt5.5125.gcc_64</value>
   </valuemap>
   <value type="QString" key="PE.Profile.DeviceTypeForIcon"></value>
   <value type="QString" key="PE.Profile.Icon"></value>
   <value type="QString" key="PE.Profile.Id">qt.qt5.5125.gcc_64_kit</value>
   <valuelist type="QVariantList" key="PE.Profile.MutableInfo"/>
   <value type="QString" key="PE.Profile.Name">Desktop Qt %{Qt:Version} GCC 64bit</value>
   <value type="bool" key="PE.Profile.SDK">true</value>
   <valuelist type="QVariantList" key="PE.Profile.StickyInfo">
    <value type="QString">QtSupport.QtInformation</value>
    <value type="QString">PE.Profile.DeviceType</value>
   </valuelist>
  </valuemap>
 </data>
 <data>
  <variable>Profile.2</variable>
  <valuemap type="QVariantMap">
   <value type="bool" key="PE.Profile.AutoDetected">false</value>
   <value type="QString" key="PE.Profile.AutoDetectionSource"></value>
   <valuemap type="QVariantMap" key="PE.Profile.Data">
    <value type="QString" key="Android.GdbServer.Information"></value>
    <valuelist type="QVariantList" key="CMake.ConfigurationKitInformation">
     <value type="QString">CMAKE_TOOLCHAIN_FILE:INTERNAL=/home/jboehme/Development/openwrt-sdk/sdk/openwrt.toolchain.cmake</value>
    </valuelist>
    <valuemap type="QVariantMap" key="CMake.GeneratorKitInformation">
     <value type="QString" key="ExtraGenerator">CodeBlocks</value>
     <value type="QString" key="Generator">Unix Makefiles</value>
     <value type="QString" key="Platform"></value>
     <value type="QString" key="Toolset"></value>
    </valuemap>
    <value type="QString" key="CMakeProjectManager.CMakeKitInformation">{9a4ea4bc-ae7e-4a8c-a1fd-57365ba1836a}</value>
    <value type="QString" key="Debugger.Information">{ed14f741-6c6a-4e81-b558-da409e3e7cc0}</value>
    <value type="QString" key="PE.Profile.Device">{db5d9aa6-9ceb-410a-b3fa-28981b07d2ef}</value>
    <value type="QString" key="PE.Profile.DeviceType">GenericLinuxOsType</value>
    <value type="QString" key="PE.Profile.SysRoot">/home/build/openwrt/staging_dir/target-i386_pentium4_musl/root-x86</value>
    <valuemap type="QVariantMap" key="PE.Profile.ToolChainsV3">
     <value type="QByteArray" key="C">{eea2dd37-a44a-4c53-aad7-cbcdfbd432c8}</value>
     <value type="QByteArray" key="Cxx">{60faf0af-86b5-4eba-9780-cd0c52fc7d13}</value>
    </valuemap>
    <value type="int" key="QtSupport.QtInformation">-1</value>
   </valuemap>
   <value type="QString" key="PE.Profile.DeviceTypeForIcon"></value>
   <value type="QString" key="PE.Profile.Icon"></value>
   <value type="QString" key="PE.Profile.Id">{4a86f510-d6ac-4ac4-ada8-8a26e5ccf538}</value>
   <valuelist type="QVariantList" key="PE.Profile.MutableInfo"/>
   <value type="QString" key="PE.Profile.Name">OpenWRT x86 32bit (pentium4)</value>
   <value type="bool" key="PE.Profile.SDK">false</value>
   <valuelist type="QVariantList" key="PE.Profile.StickyInfo"/>
  </valuemap>
 </data>
 <data>
  <variable>Profile.3</variable>
  <valuemap type="QVariantMap">
   <value type="bool" key="PE.Profile.AutoDetected">false</value>
   <value type="QString" key="PE.Profile.AutoDetectionSource"></value>
   <valuemap type="QVariantMap" key="PE.Profile.Data">
    <value type="QString" key="Android.GdbServer.Information"></value>
    <valuelist type="QVariantList" key="CMake.ConfigurationKitInformation">
     <value type="QString">CMAKE_TOOLCHAIN_FILE:INTERNAL=/home/jboehme/Development/openwrt-sdk/sdk/openwrt.toolchain.cmake</value>
    </valuelist>
    <valuemap type="QVariantMap" key="CMake.GeneratorKitInformation">
     <value type="QString" key="ExtraGenerator">CodeBlocks</value>
     <value type="QString" key="Generator">Unix Makefiles</value>
     <value type="QString" key="Platform"></value>
     <value type="QString" key="Toolset"></value>
    </valuemap>
    <value type="QString" key="CMakeProjectManager.CMakeKitInformation">{9a4ea4bc-ae7e-4a8c-a1fd-57365ba1836a}</value>
    <value type="QString" key="Debugger.Information">{87a1affb-ad10-47fe-8ebe-fda219a61a4d}</value>
    <value type="QString" key="PE.Profile.Device">{db5d9aa6-9ceb-410a-b3fa-28981b07d2ef}</value>
    <value type="QString" key="PE.Profile.DeviceType">GenericLinuxOsType</value>
    <value type="QString" key="PE.Profile.SysRoot">/home/build/openwrt/staging_dir/target-i386_pentium4_musl/root-x86</value>
    <valuemap type="QVariantMap" key="PE.Profile.ToolChainsV3">
     <value type="QByteArray" key="C">{2caabc1f-b1d9-41a0-b9ab-bb09a8dece06}</value>
     <value type="QByteArray" key="Cxx">{318bcb74-1a5d-4873-a895-199f5f86e62a}</value>
    </valuemap>
    <value type="int" key="QtSupport.QtInformation">-1</value>
   </valuemap>
   <value type="QString" key="PE.Profile.DeviceTypeForIcon"></value>
   <value type="QString" key="PE.Profile.Icon"></value>
   <value type="QString" key="PE.Profile.Id">{f6749ef3-c46a-4c89-ab1e-2afa88778f4e}</value>
   <valuelist type="QVariantList" key="PE.Profile.MutableInfo"/>
   <value type="QString" key="PE.Profile.Name">OpenWRT x86 32bit 7.4.0 (pentium4)</value>
   <value type="bool" key="PE.Profile.SDK">false</value>
   <valuelist type="QVariantList" key="PE.Profile.StickyInfo"/>
  </valuemap>
 </data>
 <data>
  <variable>Profile.4</variable>
  <valuemap type="QVariantMap">
   <value type="bool" key="PE.Profile.AutoDetected">false</value>
   <value type="QString" key="PE.Profile.AutoDetectionSource"></value>
   <valuemap type="QVariantMap" key="PE.Profile.Data">
    <value type="QString" key="Android.GdbServer.Information"></value>
    <valuelist type="QVariantList" key="CMake.ConfigurationKitInformation">
     <value type="QString">CMAKE_TOOLCHAIN_FILE:INTERNAL=/home/build/sdk/openwrt.toolchain.cmake</value>
    </valuelist>
    <valuemap type="QVariantMap" key="CMake.GeneratorKitInformation">
     <value type="QString" key="ExtraGenerator">CodeBlocks</value>
     <value type="QString" key="Generator">Unix Makefiles</value>
     <value type="QString" key="Platform"></value>
     <value type="QString" key="Toolset"></value>
    </valuemap>
    <value type="QString" key="CMakeProjectManager.CMakeKitInformation">{1eea85c6-2861-425e-ad10-561cb4b2db65}</value>
    <value type="QString" key="Debugger.Information">{7aa45a62-f81c-4fc4-abbe-3f966a8d01e0}</value>
    <value type="QString" key="PE.Profile.Device">{db5d9aa6-9ceb-410a-b3fa-28981b07d2ef}</value>
    <value type="QString" key="PE.Profile.DeviceType">GenericLinuxOsType</value>
    <value type="QString" key="PE.Profile.SysRoot">/home/build/openwrt/staging_dir/toolchain-x86_64_gcc-7.3.0_musl</value>
    <valuemap type="QVariantMap" key="PE.Profile.ToolChainsV3">
     <value type="QByteArray" key="C">{5a6ba0e0-df30-4a7c-ad3f-e1b13f1e6599}</value>
     <value type="QByteArray" key="Cxx">{3b182d8c-3b24-4006-bd63-25cacbdb989a}</value>
    </valuemap>
    <value type="int" key="QtSupport.QtInformation">-1</value>
   </valuemap>
   <value type="QString" key="PE.Profile.DeviceTypeForIcon"></value>
   <value type="QString" key="PE.Profile.Icon"></value>
   <value type="QString" key="PE.Profile.Id">{442e84d7-83d9-48c7-8dce-23acbffbd202}</value>
   <valuelist type="QVariantList" key="PE.Profile.MutableInfo"/>
   <value type="QString" key="PE.Profile.Name">OpenWRT x86 64bit 7.4.0</value>
   <value type="bool" key="PE.Profile.SDK">false</value>
   <valuelist type="QVariantList" key="PE.Profile.StickyInfo"/>
  </valuemap>
 </data>
 <data>
  <variable>Profile.5</variable>
  <valuemap type="QVariantMap">
   <value type="bool" key="PE.Profile.AutoDetected">true</value>
   <value type="QString" key="PE.Profile.AutoDetectionSource"></value>
   <valuemap type="QVariantMap" key="PE.Profile.Data">
    <valuelist type="QVariantList" key="CMake.ConfigurationKitInformation">
     <value type="QString">QT_QMAKE_EXECUTABLE:STRING=%{Qt:qmakeExecutable}</value>
     <value type="QString">CMAKE_PREFIX_PATH:STRING=%{Qt:QT_INSTALL_PREFIX}</value>
     <value type="QString">CMAKE_C_COMPILER:STRING=%{Compiler:Executable:C}</value>
     <value type="QString">CMAKE_CXX_COMPILER:STRING=%{Compiler:Executable:Cxx}</value>
    </valuelist>
    <valuemap type="QVariantMap" key="CMake.GeneratorKitInformation">
     <value type="QString" key="ExtraGenerator">CodeBlocks</value>
     <value type="QString" key="Generator">Unix Makefiles</value>
     <value type="QString" key="Platform"></value>
     <value type="QString" key="Toolset"></value>
    </valuemap>
    <value type="QString" key="CMakeProjectManager.CMakeKitInformation">{1eea85c6-2861-425e-ad10-561cb4b2db65}</value>
    <value type="QString" key="Debugger.Information">{7aa45a62-f81c-4fc4-abbe-3f966a8d01e0}</value>
    <value type="QString" key="PE.Profile.Device">Desktop Device</value>
    <value type="QString" key="PE.Profile.DeviceType">Desktop</value>
    <valuemap type="QVariantMap" key="PE.Profile.ToolChains">
     <value type="QString" key="C">x86-linux-generic-elf-64bit</value>
     <value type="QString" key="Cxx">x86-linux-generic-elf-64bit</value>
    </valuemap>
    <valuemap type="QVariantMap" key="PE.Profile.ToolChainsV3">
     <value type="QByteArray" key="C">{040a20c4-98d6-4bb4-b6c0-cd77d6c2f903}</value>
     <value type="QByteArray" key="Cxx">{57008a9f-0a5c-41af-ad89-c3f784370d39}</value>
    </valuemap>
    <value type="QString" key="QtSupport.QtInformation">SDK.qt.qt5.5126.gcc_64</value>
   </valuemap>
   <value type="QString" key="PE.Profile.DeviceTypeForIcon"></value>
   <value type="QString" key="PE.Profile.Icon"></value>
   <value type="QString" key="PE.Profile.Id">qt.qt5.5126.gcc_64_kit</value>
   <valuelist type="QVariantList" key="PE.Profile.MutableInfo"/>
   <value type="QString" key="PE.Profile.Name">Desktop Qt %{Qt:Version} GCC 64bit</value>
   <value type="bool" key="PE.Profile.SDK">true</value>
   <valuelist type="QVariantList" key="PE.Profile.StickyInfo">
    <value type="QString">QtSupport.QtInformation</value>
    <value type="QString">PE.Profile.DeviceType</value>
   </valuelist>
  </valuemap>
 </data>
 <data>
  <variable>Profile.6</variable>
  <valuemap type="QVariantMap">
   <value type="bool" key="PE.Profile.AutoDetected">true</value>
   <value type="QString" key="PE.Profile.AutoDetectionSource"></value>
   <valuemap type="QVariantMap" key="PE.Profile.Data">
    <valuelist type="QVariantList" key="CMake.ConfigurationKitInformation">
     <value type="QString">QT_QMAKE_EXECUTABLE:STRING=%{Qt:qmakeExecutable}</value>
     <value type="QString">CMAKE_PREFIX_PATH:STRING=%{Qt:QT_INSTALL_PREFIX}</value>
     <value type="QString">CMAKE_C_COMPILER:STRING=%{Compiler:Executable:C}</value>
     <value type="QString">CMAKE_CXX_COMPILER:STRING=%{Compiler:Executable:Cxx}</value>
    </valuelist>
    <valuemap type="QVariantMap" key="CMake.GeneratorKitInformation">
     <value type="QString" key="ExtraGenerator">CodeBlocks</value>
     <value type="QString" key="Generator">Unix Makefiles</value>
     <value type="QString" key="Platform"></value>
     <value type="QString" key="Toolset"></value>
    </valuemap>
    <value type="QString" key="CMakeProjectManager.CMakeKitInformation">{1eea85c6-2861-425e-ad10-561cb4b2db65}</value>
    <value type="QString" key="Debugger.Information">{7aa45a62-f81c-4fc4-abbe-3f966a8d01e0}</value>
    <value type="QString" key="PE.Profile.Device">Desktop Device</value>
    <value type="QString" key="PE.Profile.DeviceType">Desktop</value>
    <valuemap type="QVariantMap" key="PE.Profile.ToolChains">
     <value type="QString" key="C">x86-linux-generic-elf-64bit</value>
     <value type="QString" key="Cxx">x86-linux-generic-elf-64bit</value>
    </valuemap>
    <valuemap type="QVariantMap" key="PE.Profile.ToolChainsV3">
     <value type="QByteArray" key="C">{040a20c4-98d6-4bb4-b6c0-cd77d6c2f903}</value>
     <value type="QByteArray" key="Cxx">{57008a9f-0a5c-41af-ad89-c3f784370d39}</value>
    </valuemap>
    <value type="QString" key="QtSupport.QtInformation">SDK.qt.qt5.5141.gcc_64</value>
   </valuemap>
   <value type="QString" key="PE.Profile.DeviceTypeForIcon"></value>
   <value type="QString" key="PE.Profile.Icon"></value>
   <value type="QString" key="PE.Profile.Id">qt.qt5.5141.gcc_64_kit</value>
   <valuelist type="QVariantList" key="PE.Profile.MutableInfo"/>
   <value type="QString" key="PE.Profile.Name">Desktop Qt %{Qt:Version} GCC 64bit</value>
   <value type="bool" key="PE.Profile.SDK">true</value>
   <valuelist type="QVariantList" key="PE.Profile.StickyInfo">
    <value type="QString">QtSupport.QtInformation</value>
    <value type="QString">PE.Profile.DeviceType</value>
   </valuelist>
  </valuemap>
 </data>
 <data>
  <variable>Profile.7</variable>
  <valuemap type="QVariantMap">
   <value type="bool" key="PE.Profile.AutoDetected">true</value>
   <value type="QString" key="PE.Profile.AutoDetectionSource"></value>
   <valuemap type="QVariantMap" key="PE.Profile.Data">
    <valuelist type="QVariantList" key="CMake.ConfigurationKitInformation">
     <value type="QString">QT_QMAKE_EXECUTABLE:STRING=%{Qt:qmakeExecutable}</value>
     <value type="QString">CMAKE_PREFIX_PATH:STRING=%{Qt:QT_INSTALL_PREFIX}</value>
     <value type="QString">CMAKE_C_COMPILER:STRING=%{Compiler:Executable:C}</value>
     <value type="QString">CMAKE_CXX_COMPILER:STRING=%{Compiler:Executable:Cxx}</value>
    </valuelist>
    <valuemap type="QVariantMap" key="CMake.GeneratorKitInformation">
     <value type="QString" key="ExtraGenerator">CodeBlocks</value>
     <value type="QString" key="Generator">Unix Makefiles</value>
     <value type="QString" key="Platform"></value>
     <value type="QString" key="Toolset"></value>
    </valuemap>
    <value type="QString" key="CMakeProjectManager.CMakeKitInformation">{1eea85c6-2861-425e-ad10-561cb4b2db65}</value>
    <value type="QString" key="Debugger.Information">{7aa45a62-f81c-4fc4-abbe-3f966a8d01e0}</value>
    <value type="QString" key="PE.Profile.Device"></value>
    <value type="QString" key="PE.Profile.DeviceType">WebAssemblyDeviceType</value>
    <valuemap type="QVariantMap" key="PE.Profile.ToolChains">
     <value type="QString" key="C">asmjs-unknown-unknown-emscripten-32bit</value>
     <value type="QString" key="Cxx">asmjs-unknown-unknown-emscripten-32bit</value>
    </valuemap>
    <valuemap type="QVariantMap" key="PE.Profile.ToolChainsV3">
     <value type="QByteArray" key="C"></value>
     <value type="QByteArray" key="Cxx"></value>
    </valuemap>
    <value type="QString" key="QtSupport.QtInformation">SDK.qt.qt5.5141.wasm_32</value>
   </valuemap>
   <value type="QString" key="PE.Profile.DeviceTypeForIcon"></value>
   <value type="QString" key="PE.Profile.Icon"></value>
   <value type="QString" key="PE.Profile.Id">qt.qt5.5141.wasm_32_kit</value>
   <valuelist type="QVariantList" key="PE.Profile.MutableInfo"/>
   <value type="QString" key="PE.Profile.Name">Qt %{Qt:Version} WebAssembly</value>
   <value type="bool" key="PE.Profile.SDK">true</value>
   <valuelist type="QVariantList" key="PE.Profile.StickyInfo">
    <value type="QString">QtSupport.QtInformation</value>
    <value type="QString">PE.Profile.DeviceType</value>
   </valuelist>
  </valuemap>
 </data>
 <data>
  <variable>Profile.8</variable>
  <valuemap type="QVariantMap">
   <value type="bool" key="PE.Profile.AutoDetected">true</value>
   <value type="QString" key="PE.Profile.AutoDetectionSource"></value>
   <valuemap type="QVariantMap" key="PE.Profile.Data">
    <valuelist type="QVariantList" key="CMake.ConfigurationKitInformation">
     <value type="QString">QT_QMAKE_EXECUTABLE:STRING=%{Qt:qmakeExecutable}</value>
     <value type="QString">CMAKE_PREFIX_PATH:STRING=%{Qt:QT_INSTALL_PREFIX}</value>
     <value type="QString">CMAKE_C_COMPILER:STRING=%{Compiler:Executable:C}</value>
     <value type="QString">CMAKE_CXX_COMPILER:STRING=%{Compiler:Executable:Cxx}</value>
    </valuelist>
    <valuemap type="QVariantMap" key="CMake.GeneratorKitInformation">
     <value type="QString" key="ExtraGenerator">CodeBlocks</value>
     <value type="QString" key="Generator">Unix Makefiles</value>
     <value type="QString" key="Platform"></value>
     <value type="QString" key="Toolset"></value>
    </valuemap>
    <value type="QString" key="CMakeProjectManager.CMakeKitInformation">{1eea85c6-2861-425e-ad10-561cb4b2db65}</value>
    <value type="QString" key="Debugger.Information">{7aa45a62-f81c-4fc4-abbe-3f966a8d01e0}</value>
    <value type="QString" key="PE.Profile.Device">Desktop Device</value>
    <value type="QString" key="PE.Profile.DeviceType">Desktop</value>
    <valuemap type="QVariantMap" key="PE.Profile.ToolChains">
     <value type="QString" key="C">x86-linux-generic-elf-64bit</value>
     <value type="QString" key="Cxx">x86-linux-generic-elf-64bit</value>
    </valuemap>
    <valuemap type="QVariantMap" key="PE.Profile.ToolChainsV3">
     <value type="QByteArray" key="C">{040a20c4-98d6-4bb4-b6c0-cd77d6c2f903}</value>
     <value type="QByteArray" key="Cxx">{57008a9f-0a5c-41af-ad89-c3f784370d39}</value>
    </valuemap>
    <value type="QString" key="QtSupport.QtInformation">SDK.qt.qt5.5132.gcc_64</value>
   </valuemap>
   <value type="QString" key="PE.Profile.DeviceTypeForIcon"></value>
   <value type="QString" key="PE.Profile.Icon"></value>
   <value type="QString" key="PE.Profile.Id">qt.qt5.5132.gcc_64_kit</value>
   <valuelist type="QVariantList" key="PE.Profile.MutableInfo"/>
   <value type="QString" key="PE.Profile.Name">Desktop Qt %{Qt:Version} GCC 64bit</value>
   <value type="bool" key="PE.Profile.SDK">true</value>
   <valuelist type="QVariantList" key="PE.Profile.StickyInfo">
    <value type="QString">QtSupport.QtInformation</value>
    <value type="QString">PE.Profile.DeviceType</value>
   </valuelist>
  </valuemap>
 </data>
 <data>
  <variable>Profile.9</variable>
  <valuemap type="QVariantMap">
   <value type="bool" key="PE.Profile.AutoDetected">true</value>
   <value type="QString" key="PE.Profile.AutoDetectionSource"></value>
   <valuemap type="QVariantMap" key="PE.Profile.Data">
    <valuelist type="QVariantList" key="CMake.ConfigurationKitInformation">
     <value type="QString">QT_QMAKE_EXECUTABLE:STRING=%{Qt:qmakeExecutable}</value>
     <value type="QString">CMAKE_PREFIX_PATH:STRING=%{Qt:QT_INSTALL_PREFIX}</value>
     <value type="QString">CMAKE_C_COMPILER:STRING=%{Compiler:Executable:C}</value>
     <value type="QString">CMAKE_CXX_COMPILER:STRING=%{Compiler:Executable:Cxx}</value>
    </valuelist>
    <valuemap type="QVariantMap" key="CMake.GeneratorKitInformation">
     <value type="QString" key="ExtraGenerator">CodeBlocks</value>
     <value type="QString" key="Generator">Unix Makefiles</value>
     <value type="QString" key="Platform"></value>
     <value type="QString" key="Toolset"></value>
    </valuemap>
    <value type="QString" key="CMakeProjectManager.CMakeKitInformation">{1eea85c6-2861-425e-ad10-561cb4b2db65}</value>
    <value type="QString" key="Debugger.Information">{7aa45a62-f81c-4fc4-abbe-3f966a8d01e0}</value>
    <value type="QString" key="PE.Profile.Device">Desktop Device</value>
    <value type="QString" key="PE.Profile.DeviceType">Desktop</value>
    <valuemap type="QVariantMap" key="PE.Profile.ToolChainsV3"/>
    <value type="QString" key="QtSupport.QtInformation">SDK.qt.qt5.5132.wasm_32</value>
   </valuemap>
   <value type="QString" key="PE.Profile.DeviceTypeForIcon"></value>
   <value type="QString" key="PE.Profile.Icon"></value>
   <value type="QString" key="PE.Profile.Id">qt.qt5.5132.wasm_32_kit</value>
   <valuelist type="QVariantList" key="PE.Profile.MutableInfo"/>
   <value type="QString" key="PE.Profile.Name">Qt %{Qt:Version} WebAssembly</value>
   <value type="bool" key="PE.Profile.SDK">true</value>
   <valuelist type="QVariantList" key="PE.Profile.StickyInfo">
    <value type="QString">QtSupport.QtInformation</value>
    <value type="QString">PE.Profile.DeviceType</value>
   </valuelist>
  </valuemap>
 </data>
 <data>
  <variable>Profile.Count</variable>
  <value type="int">11</value>
 </data>
 <data>
  <variable>Profile.Default</variable>
  <value type="QString">{442e84d7-83d9-48c7-8dce-23acbffbd202}</value>
 </data>
 <data>
  <variable>Version</variable>
  <value type="int">1</value>
 </data>
</qtcreator>
